{
    "tableData": [
      {
        "key": "1",
        "name": "Damon",
        "volunteers": "Yes",
        "donations": "Yes",
        "description": "Description",
        "Starts": "26.10.18",
        "Ends": "26.11.18",
        "vn": 240,
        "vs": 150,
        "type": "Political",
        "location": "US"
      },
      {
        "key": "2",
        "name": "Damon",
        "volunteers": "Yes",
        "donations": "Yes",
        "description": "Description",
        "Starts": "26.10.18",
        "Ends": "26.11.18",
        "vn": 240,
        "vs": 150,
        "type": "Political",
        "location": "US"
      },
      {
        "key": "3",
        "name": "Damon",
        "volunteers": "Yes",
        "donations": "Yes",
        "description": "Description",
        "Starts": "26.10.18",
        "Ends": "26.11.18",
        "vn": 240,
        "vs": 150,
        "type": "Political",
        "location": "US"
      },
      {
        "key": "4",
        "name": "Damon",
        "volunteers": "Yes",
        "donations": "Yes",
        "description": "Description",
        "Starts": "26.10.18",
        "Ends": "26.11.18",
        "vn": 240,
        "vs": 150,
        "type": "Political",
        "location": "US"
      },
      {
        "key": "5",
        "name": "Damon",
        "volunteers": "Yes",
        "donations": "Yes",
        "description": "Description",
        "Starts": "26.10.18",
        "Ends": "26.11.18",
        "vn": 240,
        "vs": 150,
        "type": "Political",
        "location": "US"
      },
      {
        "key": "6",
        "name": "Damon",
        "volunteers": "Yes",
        "donations": "Yes",
        "description": "Description",
        "Starts": "26.10.18",
        "Ends": "26.11.18",
        "vn": 240,
        "vs": 150,
        "type": "Political",
        "location": "US"
      },
      {
        "key": "7",
        "name": "Damon",
        "volunteers": "Yes",
        "donations": "Yes",
        "description": "Description",
        "Starts": "26.10.18",
        "Ends": "26.11.18",
        "vn": 240,
        "vs": 150,
        "type": "Political",
        "location": "US"
      },
      {
        "key": "8",
        "name": "Damon",
        "volunteers": "Yes",
        "donations": "Yes",
        "description": "Description",
        "Starts": "26.10.18",
        "Ends": "26.11.18",
        "vn": 240,
        "vs": 150,
        "type": "Political",
        "location": "US"
      },
      {
        "key": "9",
        "name": "Damon",
        "volunteers": "Yes",
        "donations": "Yes",
        "description": "Description",
        "Starts": "26.10.18",
        "Ends": "26.11.18",
        "vn": 240,
        "vs": 150,
        "type": "Political",
        "location": "US"
      },
      {
        "key": "10",
        "name": "Damon",
        "volunteers": "Yes",
        "donations": "Yes",
        "description": "Description",
        "Starts": "26.10.18",
        "Ends": "26.11.18",
        "vn": 240,
        "vs": 150,
        "type": "Political",
        "location": "US"
      },
      {
        "key": "11",
        "name": "Damon",
        "volunteers": "Yes",
        "donations": "Yes",
        "description": "Description",
        "Starts": "26.10.18",
        "Ends": "26.11.18",
        "vn": 240,
        "vs": 150,
        "type": "Political",
        "location": "US"
      }
    ]
}
  